ingen/__init__.py
ingen/__main__.py
ingen/logger.py
ingen/data_source/__init__.py
ingen/data_source/api_source.py
ingen/data_source/data_source_type.py
ingen/data_source/dataframe_store.py
ingen/data_source/file_source.py
ingen/data_source/json_source.py
ingen/data_source/mysql_source.py
ingen/data_source/rawdata_source.py
ingen/data_source/source.py
ingen/data_source/source_factory.py
ingen/formatters/__init__.py
ingen/formatters/common_formatters.py
ingen/formatters/formatter.py
ingen/formatters/utils.py
ingen/generators/__init__.py
ingen/generators/base_interface_generator.py
ingen/generators/interface_generator.py
ingen/lib/__init__.py
ingen/lib/cryptor.py
ingen/metadata/__init__.py
ingen/metadata/metadata.py
ingen/metadata/metadata_parser.py
ingen/pre_processor/__init__.py
ingen/pre_processor/aggregator.py
ingen/pre_processor/aggregators.py
ingen/pre_processor/drop_duplicates.py
ingen/pre_processor/filter.py
ingen/pre_processor/mask.py
ingen/pre_processor/melt.py
ingen/pre_processor/merger.py
ingen/pre_processor/pre_processor.py
ingen/pre_processor/process.py
ingen/pre_processor/union.py
ingen/reader/__init__.py
ingen/reader/api_reader.py
ingen/reader/data_source.py
ingen/reader/file_reader.py
ingen/reader/json_reader.py
ingen/reader/mysql_reader.py
ingen/reader/rawdata_reader.py
ingen/reader/xml_file_reader.py
ingen/utils/__init__.py
ingen/utils/app_secrets.py
ingen/utils/json_df_convertors.py
ingen/utils/path_parser.py
ingen/utils/properties.py
ingen/utils/run_configuration.py
ingen/utils/sql_query_parser.py
ingen/utils/timer.py
ingen/utils/url_constructor.py
ingen/utils/utils.py
ingen/utils/app_http/__init__.py
ingen/utils/app_http/aiohttp_retry.py
ingen/utils/app_http/http_request.py
ingen/utils/app_http/http_util.py
ingen/utils/app_http/success_criterias.py
ingen/utils/interpolators/Interpolator.py
ingen/utils/interpolators/__init__.py
ingen/utils/interpolators/common_interpolators.py
ingen/validation/__init__.py
ingen/validation/common_validations.py
test_shpiyu_ig-1.0.0.dist-info/LICENSE
test_shpiyu_ig-1.0.0.dist-info/METADATA
test_shpiyu_ig-1.0.0.dist-info/WHEEL
test_shpiyu_ig-1.0.0.dist-info/top_level.txt
test_shpiyu_ig-1.0.0.dist-info/RECORD
