Metadata-Version: 2.1
Name: test-shpiyu-ig
Version: 1.0.0
Summary: A Python script suite that generates interface files based on the given interface metadata/config file
Home-page: https://github.com/blackrock/interface-generator
Maintainer: Swarna Dhakad, Piyush Ranjan, Jatin Varlyani, Pooja Katariya
Maintainer-email: swarna.dhakad@gmail.com, piyushranjan95@gmail.com, varlyanijatin88@gmail.com, poojakatariya1811@gmail.com
License: License :: Apache License
Classifier: Operating System :: OS Independent
Classifier: Programming Language :: Python :: 3.9
License-File: LICENSE
Requires-Dist: aiohttp ==3.7.*
Requires-Dist: great-expectations ==0.15.*
Requires-Dist: holidays ==0.27.*
Requires-Dist: hvac ==0.11.*
Requires-Dist: numpy ==1.21.*
Requires-Dist: pandas ==1.3.*
Requires-Dist: pycryptodome ==3.11.*
Requires-Dist: PyMySQL ==1.1.*
Requires-Dist: PyYAML ==6.0.*
Requires-Dist: setuptools ==68.0.*
Requires-Dist: xmltodict ==0.12.*
